simfaas/FunctionInstance.py
simfaas/ParFunctionInstance.py
simfaas/ParServerlessSimulator.py
simfaas/ServerlessSimulator.py
simfaas/ServerlessTemporalSimulator.py
simfaas/SimProcess.py
simfaas/Utility.py
simfaas/__init__.py
simfaas-0.2.2.dist-info/LICENSE
simfaas-0.2.2.dist-info/METADATA
simfaas-0.2.2.dist-info/WHEEL
simfaas-0.2.2.dist-info/top_level.txt
simfaas-0.2.2.dist-info/RECORD
