Metadata-Version: 2.1
Name: simfaas
Version: 0.2.2
Summary: Developed in PACS Lab as a performance simulator for serverless computing platforms.
Home-page: https://research.nima-dev.com
Author: Nima Mahmoudi
Author-email: nma@ieee.org
License: UNKNOWN
Platform: UNKNOWN
Classifier: Development Status :: 4 - Beta
Classifier: Programming Language :: Python
Classifier: Programming Language :: Python :: 3
Classifier: Programming Language :: Python :: 3.6
Classifier: Intended Audience :: Developers
Classifier: License :: OSI Approved :: MIT License
Classifier: Operating System :: OS Independent
Requires-Dist: numpy (>=1.18.4)
Requires-Dist: matplotlib (>=3.2.1)
Requires-Dist: pandas (>=1.0.3)
Requires-Dist: scipy (>=1.4.1)
Requires-Dist: tqdm (>=4.46.0)
